gtrbench/__init__.py
gtrbench/base.py
gtrbench/util.py
gtrbench/picnic/__init__.py
gtrbench/picnic/dynamic_picnic/__init__.py
gtrbench/picnic/dynamic_picnic/base.py
gtrbench/picnic/dynamic_picnic/test.py
gtrbench/picnic/function_picnic/__init__.py
gtrbench/picnic/function_picnic/base.py
gtrbench/picnic/static_picnic/__init__.py
gtrbench/picnic/static_picnic/base.py
gtrbench/picnic/static_picnic/helper_google_openimages_process_items.py
tests/__init__.py
tests/static_picnic.py
gtrbench-0.0.1.dist-info/LICENSE
gtrbench-0.0.1.dist-info/METADATA
gtrbench-0.0.1.dist-info/WHEEL
gtrbench-0.0.1.dist-info/top_level.txt
gtrbench-0.0.1.dist-info/RECORD
