Metadata-Version: 2.1
Name: gtrbench
Version: 0.0.1
Summary: A benchmark to evaluate implicit reasoning in LLMs using guess-the-rule games
Home-page: UNKNOWN
Author: Ali Shazal (with Michael Lu, Xiang Zheng, Juno Lee, Arihant Choudhary)
Author-email: ali.shazal@berkeley.edu
License: MIT
Keywords: benchmark,llm,implicit reasoning,guess-the-rule games,gtrbench
Platform: UNKNOWN
Classifier: Development Status :: 3 - Alpha
Classifier: Programming Language :: Python :: 3
Classifier: Intended Audience :: Science/Research
Classifier: License :: OSI Approved :: MIT License
Classifier: Operating System :: OS Independent
Requires-Python: >=3.7
License-File: LICENSE
Requires-Dist: openai==1.56.0
Requires-Dist: python-dotenv==1.0.0
Requires-Dist: nltk==3.8.1
Requires-Dist: anthropic==0.3.0
Requires-Dist: retry==0.9.2
Requires-Dist: google-generativeai==0.3.2
Provides-Extra: dev
Requires-Dist: black==23.7.0; extra == "dev"
Requires-Dist: flake8==6.1.0; extra == "dev"
Provides-Extra: test
Requires-Dist: pytest==7.3.1; extra == "test"
Requires-Dist: httpx==0.24.0; extra == "test"
